flask_thumbnails/__init__.py
flask_thumbnails/storage_backends.py
flask_thumbnails/thumbnail.py
flask_thumbnails/utils.py
Flask_thumbnails-1.1.0.dist-info/LICENSE
Flask_thumbnails-1.1.0.dist-info/METADATA
Flask_thumbnails-1.1.0.dist-info/WHEEL
Flask_thumbnails-1.1.0.dist-info/top_level.txt
Flask_thumbnails-1.1.0.dist-info/RECORD
